nsma/algorithms/__init__.py
nsma/algorithms/algorithm.py
nsma/algorithms/algorithm_factory.py
nsma/algorithms/algorithm_utils/__init__.py
nsma/algorithms/algorithm_utils/graphical_plot.py
nsma/algorithms/algorithm_utils/stopping_condition.py
nsma/algorithms/algorithm_utils/verbose_system.py
nsma/algorithms/genetic/__init__.py
nsma/algorithms/genetic/genetic_algorithm.py
nsma/algorithms/genetic/nsga_ii.py
nsma/algorithms/genetic/genetic_utils/__init__.py
nsma/algorithms/genetic/genetic_utils/general_utils.py
nsma/algorithms/genetic/genetic_utils/survival_strategy.py
nsma/algorithms/gradient_based/__init__.py
nsma/algorithms/gradient_based/gradient_based_algorithm.py
nsma/algorithms/gradient_based/local_search_algorithms/__init__.py
nsma/algorithms/gradient_based/local_search_algorithms/fmopg.py
nsma/algorithms/gradient_based/local_search_algorithms/local_search_algorithm_factory.py
nsma/algorithms/memetic/__init__.py
nsma/algorithms/memetic/memetic_algorithm.py
nsma/algorithms/memetic/nsma.py
nsma/algorithms/memetic/memetic_utils/__init__.py
nsma/algorithms/memetic/memetic_utils/survival_strategy.py
nsma/direction_solvers/__init__.py
nsma/direction_solvers/direction_solver_factory.py
nsma/direction_solvers/gurobi_settings.py
nsma/direction_solvers/descent_direction/__init__.py
nsma/direction_solvers/descent_direction/boundconstrained_projected_gradient_dds_gurobi_version.py
nsma/direction_solvers/descent_direction/boundconstrained_projected_gradient_dds_scipy_version.py
nsma/direction_solvers/descent_direction/dds.py
nsma/general_utils/__init__.py
nsma/general_utils/pareto_utils.py
nsma/line_searches/__init__.py
nsma/line_searches/line_search_factory.py
nsma/line_searches/armijo_type/__init__.py
nsma/line_searches/armijo_type/als.py
nsma/line_searches/armijo_type/boundconstrained_front_als.py
nsma/line_searches/line_search_utils/__init__.py
nsma/line_searches/line_search_utils/pareto_utils.py
nsma/problems/__init__.py
nsma/problems/problem.py
nsma-1.0.14.dist-info/LICENSE
nsma-1.0.14.dist-info/METADATA
nsma-1.0.14.dist-info/WHEEL
nsma-1.0.14.dist-info/top_level.txt
nsma-1.0.14.dist-info/RECORD
