Metadata-Version: 2.1
Name: nsma
Version: 1.0.14
Summary: NSMA: A Memetic Procedure for Global Multi-Objective Optimization.
Author-email: Mansueto Pierluigi <pierluigimansueto@gmail.com>
License: Apache License 2.0
Project-URL: Homepage, https://github.com/pierlumanzu/nsma
Project-URL: Tracker, https://github.com/pierlumanzu/nsma/issues
Keywords: Multi-objective optimization,Memetic algorithm,NSGA-II,Descent method,Pareto front approximation
Classifier: Development Status :: 5 - Production/Stable
Classifier: License :: OSI Approved :: Apache Software License
Classifier: Operating System :: Microsoft :: Windows
Classifier: Operating System :: MacOS
Classifier: Operating System :: POSIX :: Linux
Classifier: Programming Language :: Python :: 3.10
Classifier: Topic :: Scientific/Engineering :: Mathematics
Requires-Python: >=3.9
License-File: LICENSE
Requires-Dist: progressbar2 >=4.2.0
Requires-Dist: gurobipy >=9.5.2
Requires-Dist: numpy >=1.22.3
Requires-Dist: scipy >=1.7.3
Requires-Dist: matplotlib >=3.6.1 ; platform_system == "Darwin"
Requires-Dist: tensorflow >=2.10.0 ; platform_system == "Darwin"
Requires-Dist: pyqt5 >=5.15.7 ; platform_system == "Darwin"
Requires-Dist: matplotlib >=3.5.2 ; platform_system == "Linux"
Requires-Dist: tensorflow >=2.8.2 ; platform_system == "Linux"
Requires-Dist: matplotlib >=3.5.3 ; platform_system == "Windows"
Requires-Dist: tensorflow >=2.9.1 ; platform_system == "Windows"
